prints_charming/__init__.py
prints_charming/color_maps.py
prints_charming/colors_wizard.py
prints_charming/dynamic_formatter.py
prints_charming/formatter.py
prints_charming/frame_builder.py
prints_charming/interactive_menu.py
prints_charming/interactive_wizard.py
prints_charming/internal_logging_utils.py
prints_charming/markdown_processor.py
prints_charming/prints_charming.py
prints_charming/prints_charming_defaults.py
prints_charming/prints_style.py
prints_charming/prints_ui.py
prints_charming/progress_bar.py
prints_charming/segment_styler.py
prints_charming/table_manager.py
prints_charming/terminal_manager.py
prints_charming/terminal_size_watcher.py
prints_charming/toggle_manager.py
prints_charming/trie_manager.py
prints_charming/utils.py
prints_charming/win_utils.py
prints_charming/examples/__init__.py
prints_charming/examples/basic_exception_logging.py
prints_charming/examples/basic_logging.py
prints_charming/examples/calc_example.py
prints_charming/examples/exceptions_example.py
prints_charming/examples/frames.py
prints_charming/examples/main.py
prints_charming/examples/markdown.py
prints_charming/examples/maze.py
prints_charming/examples/menu.py
prints_charming/examples/multi_column_boxes.py
prints_charming/examples/patterns.py
prints_charming/examples/segment_with_splitter_and_style.py
prints_charming/examples/snake_game.py
prints_charming/exceptions/__init__.py
prints_charming/exceptions/base_exceptions.py
prints_charming/exceptions/internal_exceptions.py
prints_charming/exceptions/utils.py
prints_charming/internal_logging/__init__.py
prints_charming/internal_logging/log_manager.py
prints_charming/logging/__init__.py
prints_charming/logging/formatter.py
prints_charming/logging/log_handler.py
prints_charming/regex_patterns/__init__.py
prints_charming/regex_patterns/ansi_patterns.py
prints_charming/regex_patterns/whitespace_patterns.py
prints_charming/settings/__init__.py
prints_charming/settings/color_maps.py
prints_charming/settings/effect_maps.py
prints_charming-2.0.0.dist-info/LICENSE
prints_charming-2.0.0.dist-info/METADATA
prints_charming-2.0.0.dist-info/WHEEL
prints_charming-2.0.0.dist-info/top_level.txt
prints_charming-2.0.0.dist-info/RECORD
