Metadata-Version: 2.2
Name: prints_charming
Version: 2.0.0
Summary: The Ultimate Toolkit for Terminal Interfaces, Text Styling, and Advanced Functionality.
Home-page: https://github.com/deefifofun/prints_charming
Author: DeeFiFoFun
Author-email: dev@deefifofun.xyz
Requires-Python: >=3.10
License-File: LICENSE
Dynamic: author
Dynamic: author-email
Dynamic: home-page
Dynamic: summary
